{
  "#umlaut_a": {
    "takemetospace_": {
      "nMsg": 255,
      "avgWordCount": 3.8549019607843125
    },
    "Spiral3Y3S": {
      "nMsg": 126,
      "avgWordCount": 4.642857142857145
    },
    "CoachRicashea": {
      "nMsg": 29,
      "avgWordCount": 2.793103448275862
    },
    "BlueHighway": {
      "nMsg": 26,
      "avgWordCount": 7.576923076923077
    },
    "Lukeski14": {
      "nMsg": 41,
      "avgWordCount": 4.756097560975611
    },
    "CultBot_A": {
      "nMsg": 9,
      "avgWordCount": 6.222222222222222
    },
    "twisstedshadow1423": {
      "nMsg": 2,
      "avgWordCount": 5
    },
    "rumzinna": {
      "nMsg": 8,
      "avgWordCount": 6.125
    },
    "bezosfan1": {
      "nMsg": 235,
      "avgWordCount": 5.553191489361702
    },
    "ToBeQuiteFranky": {
      "nMsg": 45,
      "avgWordCount": 6.288888888888889
    },
    "xxloud_assassinxx": {
      "nMsg": 30,
      "avgWordCount": 11.866666666666667
    },
    "Telos_OW": {
      "nMsg": 3,
      "avgWordCount": 7
    },
    "IsJovial": {
      "nMsg": 2,
      "avgWordCount": 3
    },
    "AESTIGE": {
      "nMsg": 7,
      "avgWordCount": 4.428571428571429
    },
    "DanGleesack": {
      "nMsg": 3,
      "avgWordCount": 2.6666666666666665
    },
    "Undead_Logic": {
      "nMsg": 78,
      "avgWordCount": 4.833333333333334
    },
    "Brycebat": {
      "nMsg": 2,
      "avgWordCount": 6.5
    },
    "j15y9rkp": {
      "nMsg": 25,
      "avgWordCount": 9.239999999999998
    },
    "Umlaut_A": {
      "nMsg": 1,
      "avgWordCount": 1
    }
  },
  "#trexcapades": {
    "DarthVandigo": {
      "nMsg": 1,
      "avgWordCount": 1
    },
    "mickfoley": {
      "nMsg": 1,
      "avgWordCount": 2
    }
  },
  "#hutch": {
    "asadqqs": {
      "nMsg": 1,
      "avgWordCount": 1
    },
    "ateateight": {
      "nMsg": 123,
      "avgWordCount": 7.861788617886175
    },
    "palestinian_denzel": {
      "nMsg": 13,
      "avgWordCount": 6.230769230769231
    },
    "Drop_the_Mike": {
      "nMsg": 4,
      "avgWordCount": 4
    },
    "Nickki19": {
      "nMsg": 1,
      "avgWordCount": 7
    },
    "Jungle_jims99": {
      "nMsg": 3,
      "avgWordCount": 2
    },
    "vython1": {
      "nMsg": 1,
      "avgWordCount": 6
    },
    "iwoutah": {
      "nMsg": 102,
      "avgWordCount": 7.254901960784314
    },
    "badstellar": {
      "nMsg": 1,
      "avgWordCount": 1
    },
    "Evan_bYd": {
      "nMsg": 5,
      "avgWordCount": 3.4
    },
    "Undead_Logic": {
      "nMsg": 67,
      "avgWordCount": 8.01492537313433
    },
    "tloyd16": {
      "nMsg": 22,
      "avgWordCount": 4.8181818181818175
    },
    "j15y9rkp": {
      "nMsg": 256,
      "avgWordCount": 4.531250000000001
    },
    "SageModeHelen": {
      "nMsg": 8,
      "avgWordCount": 20.5
    },
    "Bowlcut7467": {
      "nMsg": 36,
      "avgWordCount": 5
    },
    "bird_lawyer74": {
      "nMsg": 86,
      "avgWordCount": 7.674418604651163
    },
    "action_gordon": {
      "nMsg": 18,
      "avgWordCount": 5.111111111111111
    },
    "MrTenenbaum": {
      "nMsg": 1,
      "avgWordCount": 2
    },
    "Nightbot": {
      "nMsg": 100,
      "avgWordCount": 19.030000000000015
    },
    "Curtis6405": {
      "nMsg": 84,
      "avgWordCount": 6.2261904761904745
    },
    "bock72": {
      "nMsg": 1,
      "avgWordCount": 2
    },
    "EdenFire108": {
      "nMsg": 1,
      "avgWordCount": 1
    },
    "AnnoyingAsian": {
      "nMsg": 22,
      "avgWordCount": 2.227272727272727
    },
    "Tetraquatic": {
      "nMsg": 1,
      "avgWordCount": 3
    },
    "percypig18": {
      "nMsg": 1,
      "avgWordCount": 5
    },
    "DanGleesack": {
      "nMsg": 25,
      "avgWordCount": 2
    },
    "DG_Hippie": {
      "nMsg": 42,
      "avgWordCount": 4.976190476190476
    },
    "TrebleDriver": {
      "nMsg": 14,
      "avgWordCount": 6.285714285714286
    },
    "S__Bharmal": {
      "nMsg": 320,
      "avgWordCount": 5.30625
    },
    "itskideo": {
      "nMsg": 8,
      "avgWordCount": 6
    },
    "Uncle_Weird_Hug": {
      "nMsg": 1,
      "avgWordCount": 9
    },
    "Nekshul": {
      "nMsg": 50,
      "avgWordCount": 3.44
    },
    "DavinCiSki": {
      "nMsg": 150,
      "avgWordCount": 4.039999999999999
    },
    "JayDizL": {
      "nMsg": 5,
      "avgWordCount": 3.8
    },
    "meepmorp1348": {
      "nMsg": 2,
      "avgWordCount": 2
    },
    "fathertingle": {
      "nMsg": 2,
      "avgWordCount": 3.5
    },
    "luciankhalid": {
      "nMsg": 1,
      "avgWordCount": 1
    },
    "erockpls": {
      "nMsg": 1,
      "avgWordCount": 1
    },
    "elenanumbers_": {
      "nMsg": 124,
      "avgWordCount": 4.75
    },
    "Michael_farre": {
      "nMsg": 2,
      "avgWordCount": 2
    },
    "RonaldFSpears": {
      "nMsg": 13,
      "avgWordCount": 2.3846153846153846
    },
    "SirLazyBlue": {
      "nMsg": 1,
      "avgWordCount": 1
    },
    "TheIncoherentGamer": {
      "nMsg": 5,
      "avgWordCount": 5.4
    },
    "bikstar09": {
      "nMsg": 10,
      "avgWordCount": 5.6
    },
    "Orion2325": {
      "nMsg": 10,
      "avgWordCount": 5.8
    },
    "BigBsquared": {
      "nMsg": 4,
      "avgWordCount": 7.75
    },
    "FRANK_GAMBINO": {
      "nMsg": 66,
      "avgWordCount": 4.9696969696969715
    },
    "fredtwentytwenty": {
      "nMsg": 1,
      "avgWordCount": 1
    },
    "Euph1993": {
      "nMsg": 36,
      "avgWordCount": 3.8888888888888906
    },
    "headclic": {
      "nMsg": 1,
      "avgWordCount": 1
    },
    "flamboyant_username": {
      "nMsg": 1,
      "avgWordCount": 1
    },
    "TinnyHipp0": {
      "nMsg": 1,
      "avgWordCount": 2
    },
    "janken888": {
      "nMsg": 39,
      "avgWordCount": 6.230769230769231
    },
    "saucygandalf": {
      "nMsg": 1,
      "avgWordCount": 2
    },
    "benenarthur": {
      "nMsg": 2,
      "avgWordCount": 2.5
    },
    "lonecamper": {
      "nMsg": 1,
      "avgWordCount": 1
    },
    "what_hook": {
      "nMsg": 3,
      "avgWordCount": 1.6666666666666667
    },
    "chi3f_k33f": {
      "nMsg": 1,
      "avgWordCount": 1
    },
    "shri07vora": {
      "nMsg": 3,
      "avgWordCount": 4.333333333333333
    },
    "mendezu23": {
      "nMsg": 42,
      "avgWordCount": 5.428571428571429
    },
    "crushing2013": {
      "nMsg": 43,
      "avgWordCount": 7.511627906976744
    },
    "mass2": {
      "nMsg": 8,
      "avgWordCount": 5.625
    },
    "DerBerger61": {
      "nMsg": 1,
      "avgWordCount": 18
    },
    "LankyDragoon": {
      "nMsg": 4,
      "avgWordCount": 4.75
    },
    "saturnine5": {
      "nMsg": 6,
      "avgWordCount": 7.166666666666667
    },
    "chriswithguns": {
      "nMsg": 1,
      "avgWordCount": 16
    },
    "Megadon88": {
      "nMsg": 25,
      "avgWordCount": 4.360000000000001
    },
    "AlmondPDK": {
      "nMsg": 2,
      "avgWordCount": 3.5
    },
    "teedubs21": {
      "nMsg": 114,
      "avgWordCount": 4.333333333333332
    },
    "DenimAndLead": {
      "nMsg": 3,
      "avgWordCount": 4.666666666666667
    },
    "cfixed": {
      "nMsg": 1,
      "avgWordCount": 5
    },
    "berimu": {
      "nMsg": 7,
      "avgWordCount": 4.142857142857143
    },
    "Mazap15": {
      "nMsg": 2,
      "avgWordCount": 4.5
    },
    "nascar_nahmann": {
      "nMsg": 32,
      "avgWordCount": 12.75
    },
    "jwise32": {
      "nMsg": 1,
      "avgWordCount": 15
    },
    "Funnyfreek": {
      "nMsg": 4,
      "avgWordCount": 3.5
    },
    "MajorAllSham": {
      "nMsg": 76,
      "avgWordCount": 5.289473684210527
    },
    "milesdei7": {
      "nMsg": 1,
      "avgWordCount": 3
    },
    "Dygo1": {
      "nMsg": 33,
      "avgWordCount": 3.4545454545454546
    },
    "StopAndChat": {
      "nMsg": 239,
      "avgWordCount": 4.196652719665274
    },
    "wekilledit": {
      "nMsg": 2,
      "avgWordCount": 10.5
    },
    "chiefsnugglebug": {
      "nMsg": 3,
      "avgWordCount": 6.333333333333333
    },
    "shahnabil79": {
      "nMsg": 1,
      "avgWordCount": 14
    },
    "BruceyGooseyy": {
      "nMsg": 4,
      "avgWordCount": 2.75
    },
    "biggermuff": {
      "nMsg": 3,
      "avgWordCount": 2.6666666666666665
    },
    "dayboyrobbywill": {
      "nMsg": 1,
      "avgWordCount": 6
    },
    "sourlemmon": {
      "nMsg": 4,
      "avgWordCount": 4.5
    },
    "theBadgr": {
      "nMsg": 35,
      "avgWordCount": 6.285714285714286
    },
    "CraZPants": {
      "nMsg": 5,
      "avgWordCount": 6.4
    },
    "adamali9655": {
      "nMsg": 1,
      "avgWordCount": 20
    },
    "sssware": {
      "nMsg": 4,
      "avgWordCount": 9.5
    },
    "TomDcat": {
      "nMsg": 10,
      "avgWordCount": 9.9
    },
    "Bilbo_Lagginz": {
      "nMsg": 15,
      "avgWordCount": 3.4
    },
    "sub2j15": {
      "nMsg": 34,
      "avgWordCount": 10.411764705882353
    },
    "goobtron_2000": {
      "nMsg": 1,
      "avgWordCount": 1
    },
    "DmoGaming": {
      "nMsg": 19,
      "avgWordCount": 4.842105263157895
    },
    "Sundin00013": {
      "nMsg": 8,
      "avgWordCount": 4
    },
    "myolthir": {
      "nMsg": 1,
      "avgWordCount": 10
    },
    "ydooWoody": {
      "nMsg": 1,
      "avgWordCount": 3
    },
    "Madslie": {
      "nMsg": 16,
      "avgWordCount": 5.625
    },
    "Mariopapc": {
      "nMsg": 6,
      "avgWordCount": 11.666666666666666
    },
    "lostpriorities": {
      "nMsg": 8,
      "avgWordCount": 10.125
    },
    "TheSaucyLou": {
      "nMsg": 1,
      "avgWordCount": 6
    },
    "ChiefMasterKief": {
      "nMsg": 1,
      "avgWordCount": 3
    },
    "xNailgunx": {
      "nMsg": 1,
      "avgWordCount": 4
    },
    "SwankyBaller": {
      "nMsg": 4,
      "avgWordCount": 3
    },
    "davideo68": {
      "nMsg": 2,
      "avgWordCount": 5
    },
    "nickdietrich": {
      "nMsg": 2,
      "avgWordCount": 15
    },
    "snorca": {
      "nMsg": 25,
      "avgWordCount": 4.64
    },
    "sleept1ght": {
      "nMsg": 5,
      "avgWordCount": 2
    },
    "big_lng": {
      "nMsg": 10,
      "avgWordCount": 2.6
    },
    "mannysecksbang": {
      "nMsg": 3,
      "avgWordCount": 4
    },
    "BlackTuna4581": {
      "nMsg": 5,
      "avgWordCount": 2.6
    },
    "godskillskanade": {
      "nMsg": 1,
      "avgWordCount": 2
    },
    "Nic_At_Nite84": {
      "nMsg": 4,
      "avgWordCount": 3
    },
    "SpareHourGaming": {
      "nMsg": 1,
      "avgWordCount": 8
    },
    "nardbarge": {
      "nMsg": 3,
      "avgWordCount": 6.666666666666667
    },
    "B_As_In_Bacon": {
      "nMsg": 3,
      "avgWordCount": 3
    },
    "AllyKazamn": {
      "nMsg": 1,
      "avgWordCount": 8
    },
    "dannyf91": {
      "nMsg": 1,
      "avgWordCount": 5
    },
    "WellerFM": {
      "nMsg": 1,
      "avgWordCount": 1
    },
    "feudal_tennis_knight": {
      "nMsg": 1,
      "avgWordCount": 1
    },
    "jay__tay": {
      "nMsg": 1,
      "avgWordCount": 3
    },
    "Brycebat": {
      "nMsg": 17,
      "avgWordCount": 4.529411764705882
    },
    "Headsmen": {
      "nMsg": 61,
      "avgWordCount": 4.573770491803279
    },
    "CesarRivers": {
      "nMsg": 5,
      "avgWordCount": 6
    },
    "tyler_tree191": {
      "nMsg": 14,
      "avgWordCount": 6.5
    },
    "Platfoot": {
      "nMsg": 14,
      "avgWordCount": 8.857142857142858
    },
    "four4oh": {
      "nMsg": 2,
      "avgWordCount": 4
    },
    "VinceThePince_": {
      "nMsg": 12,
      "avgWordCount": 4.75
    },
    "Tomnero": {
      "nMsg": 2,
      "avgWordCount": 9.5
    },
    "WaitThatsNotLegal": {
      "nMsg": 44,
      "avgWordCount": 5.75
    },
    "millamojay": {
      "nMsg": 3,
      "avgWordCount": 4.666666666666667
    },
    "TeresMajor": {
      "nMsg": 2,
      "avgWordCount": 4.5
    },
    "allbeefpattiez": {
      "nMsg": 2,
      "avgWordCount": 4
    },
    "Mrgrimm3": {
      "nMsg": 1,
      "avgWordCount": 13
    },
    "69devinthedude69": {
      "nMsg": 2,
      "avgWordCount": 10.5
    },
    "hallmorales": {
      "nMsg": 89,
      "avgWordCount": 7.47191011235955
    },
    "Conkreet": {
      "nMsg": 21,
      "avgWordCount": 5.285714285714286
    },
    "HopscotchBeaver": {
      "nMsg": 1,
      "avgWordCount": 5
    },
    "Jayv2004": {
      "nMsg": 1,
      "avgWordCount": 2
    },
    "Yng_sketti": {
      "nMsg": 1,
      "avgWordCount": 4
    },
    "kopite99": {
      "nMsg": 7,
      "avgWordCount": 4.857142857142857
    },
    "seancbo": {
      "nMsg": 3,
      "avgWordCount": 10.333333333333334
    },
    "kobeykg3": {
      "nMsg": 3,
      "avgWordCount": 4.333333333333333
    },
    "Chineeman": {
      "nMsg": 2,
      "avgWordCount": 6
    },
    "axonIvorist": {
      "nMsg": 1,
      "avgWordCount": 4
    },
    "danieldo": {
      "nMsg": 4,
      "avgWordCount": 5
    },
    "MrMojoRisin9": {
      "nMsg": 2,
      "avgWordCount": 5.5
    },
    "lookitsmp": {
      "nMsg": 1,
      "avgWordCount": 1
    },
    "ctanderson21": {
      "nMsg": 1,
      "avgWordCount": 5
    },
    "MIsterremix99": {
      "nMsg": 9,
      "avgWordCount": 3.111111111111111
    },
    "meowarco": {
      "nMsg": 14,
      "avgWordCount": 2.5000000000000004
    },
    "SofaKing0": {
      "nMsg": 5,
      "avgWordCount": 3.4
    },
    "nickknorth": {
      "nMsg": 2,
      "avgWordCount": 11
    },
    "Josejayrivas": {
      "nMsg": 3,
      "avgWordCount": 4.666666666666667
    },
    "rosaparks6969": {
      "nMsg": 1,
      "avgWordCount": 16
    },
    "jollysugarkush": {
      "nMsg": 21,
      "avgWordCount": 5.619047619047619
    },
    "osocereal": {
      "nMsg": 1,
      "avgWordCount": 1
    },
    "HeroJackBauer": {
      "nMsg": 2,
      "avgWordCount": 12
    },
    "RagingIrishMan98": {
      "nMsg": 29,
      "avgWordCount": 5.344827586206897
    },
    "patch413": {
      "nMsg": 2,
      "avgWordCount": 7
    },
    "Riicta": {
      "nMsg": 1,
      "avgWordCount": 8
    },
    "attivx": {
      "nMsg": 1,
      "avgWordCount": 6
    },
    "cormac700": {
      "nMsg": 1,
      "avgWordCount": 4
    },
    "tsunami_33": {
      "nMsg": 1,
      "avgWordCount": 5
    },
    "Scott_TV": {
      "nMsg": 1,
      "avgWordCount": 3
    },
    "Jedddy": {
      "nMsg": 2,
      "avgWordCount": 1
    },
    "martinfloresmusic": {
      "nMsg": 4,
      "avgWordCount": 1.75
    },
    "bgs1992": {
      "nMsg": 1,
      "avgWordCount": 7
    },
    "IISHOWERHANDLEII": {
      "nMsg": 8,
      "avgWordCount": 6.375
    },
    "TheGoodSirFlankalot": {
      "nMsg": 4,
      "avgWordCount": 6.75
    },
    "carnage_falcon": {
      "nMsg": 27,
      "avgWordCount": 5.518518518518518
    },
    "27matt27": {
      "nMsg": 86,
      "avgWordCount": 6.976744186046512
    },
    "rinnzzlerr": {
      "nMsg": 8,
      "avgWordCount": 6.625
    },
    "jebigahrv": {
      "nMsg": 1,
      "avgWordCount": 8
    },
    "wotds03": {
      "nMsg": 1,
      "avgWordCount": 6
    },
    "jay94us": {
      "nMsg": 10,
      "avgWordCount": 3.6
    },
    "TheBrutal95": {
      "nMsg": 11,
      "avgWordCount": 5.2727272727272725
    },
    "Nk15_": {
      "nMsg": 41,
      "avgWordCount": 5.146341463414634
    },
    "BRAN822222": {
      "nMsg": 18,
      "avgWordCount": 4.888888888888889
    },
    "D_FENS3": {
      "nMsg": 13,
      "avgWordCount": 4.692307692307692
    },
    "Beejlejuice": {
      "nMsg": 5,
      "avgWordCount": 4.4
    },
    "daxirealraw": {
      "nMsg": 6,
      "avgWordCount": 3.6666666666666665
    },
    "justbeingjessica": {
      "nMsg": 10,
      "avgWordCount": 2.3
    },
    "wizhwizz": {
      "nMsg": 6,
      "avgWordCount": 5.333333333333333
    },
    "MarkDaBearded": {
      "nMsg": 25,
      "avgWordCount": 4.24
    },
    "LarsPantsOnFars": {
      "nMsg": 2,
      "avgWordCount": 6.5
    },
    "SupaDupa9": {
      "nMsg": 1,
      "avgWordCount": 9
    },
    "Spiral3Y3S": {
      "nMsg": 9,
      "avgWordCount": 3.888888888888889
    },
    "mrpearl4twenty": {
      "nMsg": 1,
      "avgWordCount": 9
    },
    "DopamineGene": {
      "nMsg": 1,
      "avgWordCount": 5
    },
    "mattysakic": {
      "nMsg": 1,
      "avgWordCount": 6
    },
    "idkvincenzo": {
      "nMsg": 2,
      "avgWordCount": 3.5
    },
    "Jrcbeland": {
      "nMsg": 3,
      "avgWordCount": 1.6666666666666667
    },
    "cAngelitoBebito": {
      "nMsg": 1,
      "avgWordCount": 1
    },
    "pumpernickelback": {
      "nMsg": 1,
      "avgWordCount": 1
    },
    "HuskyCorpse": {
      "nMsg": 7,
      "avgWordCount": 3.2857142857142856
    },
    "MarioPlayer2OO": {
      "nMsg": 1,
      "avgWordCount": 1
    },
    "Whatisup12": {
      "nMsg": 1,
      "avgWordCount": 1
    },
    "mkid5": {
      "nMsg": 1,
      "avgWordCount": 1
    },
    "sagers69": {
      "nMsg": 1,
      "avgWordCount": 1
    },
    "Richslice": {
      "nMsg": 8,
      "avgWordCount": 6.5
    },
    "VictraAuBarca12": {
      "nMsg": 11,
      "avgWordCount": 5.181818181818182
    },
    "AlephBeyet": {
      "nMsg": 4,
      "avgWordCount": 1
    },
    "MylesA2112": {
      "nMsg": 2,
      "avgWordCount": 2
    },
    "Casting_Couch": {
      "nMsg": 3,
      "avgWordCount": 2
    },
    "ocoolenergyo": {
      "nMsg": 1,
      "avgWordCount": 1
    },
    "fillgee": {
      "nMsg": 7,
      "avgWordCount": 6.285714285714286
    },
    "tspear17": {
      "nMsg": 1,
      "avgWordCount": 2
    },
    "Zearoph": {
      "nMsg": 2,
      "avgWordCount": 2
    },
    "CatalystiCrisis": {
      "nMsg": 2,
      "avgWordCount": 2
    },
    "Pickledshrimp": {
      "nMsg": 1,
      "avgWordCount": 1
    },
    "dylquad": {
      "nMsg": 4,
      "avgWordCount": 3
    },
    "cluelesseuropean": {
      "nMsg": 1,
      "avgWordCount": 2
    },
    "majormortyy": {
      "nMsg": 1,
      "avgWordCount": 1
    },
    "douglas201288": {
      "nMsg": 1,
      "avgWordCount": 4
    },
    "swatricpayze": {
      "nMsg": 14,
      "avgWordCount": 7.5
    },
    "PlujaDeCor": {
      "nMsg": 2,
      "avgWordCount": 10
    },
    "ThatFunnyBanana": {
      "nMsg": 4,
      "avgWordCount": 10.25
    },
    "BearDown26": {
      "nMsg": 13,
      "avgWordCount": 4.153846153846154
    },
    "mister__maze": {
      "nMsg": 1,
      "avgWordCount": 1
    },
    "germy_lean": {
      "nMsg": 2,
      "avgWordCount": 6
    },
    "ChalupaGrande": {
      "nMsg": 8,
      "avgWordCount": 2.5
    },
    "TyCrunk": {
      "nMsg": 1,
      "avgWordCount": 7
    },
    "weighm": {
      "nMsg": 2,
      "avgWordCount": 2
    },
    "wrinklypinkybinky": {
      "nMsg": 2,
      "avgWordCount": 3
    },
    "0swaldthatendswald": {
      "nMsg": 4,
      "avgWordCount": 6
    },
    "jphil_04": {
      "nMsg": 3,
      "avgWordCount": 2
    },
    "nikolai0527": {
      "nMsg": 4,
      "avgWordCount": 1.75
    },
    "gza0909": {
      "nMsg": 21,
      "avgWordCount": 8.428571428571429
    },
    "Raging2Lego123": {
      "nMsg": 1,
      "avgWordCount": 2
    },
    "tbob27": {
      "nMsg": 2,
      "avgWordCount": 6.5
    },
    "duke_smoochem": {
      "nMsg": 1,
      "avgWordCount": 8
    },
    "tomway_": {
      "nMsg": 1,
      "avgWordCount": 1
    },
    "LiveCustoms": {
      "nMsg": 1,
      "avgWordCount": 1
    },
    "Kielbosa": {
      "nMsg": 36,
      "avgWordCount": 4.166666666666667
    },
    "loganchan_cellor": {
      "nMsg": 1,
      "avgWordCount": 1
    },
    "blacknewman": {
      "nMsg": 3,
      "avgWordCount": 4
    },
    "VengefulFiend": {
      "nMsg": 38,
      "avgWordCount": 10.921052631578947
    },
    "dunny_budgie": {
      "nMsg": 2,
      "avgWordCount": 7
    },
    "Haloxgears": {
      "nMsg": 1,
      "avgWordCount": 10
    },
    "The_LordCabbage": {
      "nMsg": 4,
      "avgWordCount": 4.25
    },
    "XcellentSkillz": {
      "nMsg": 1,
      "avgWordCount": 12
    },
    "Leroy686": {
      "nMsg": 1,
      "avgWordCount": 6
    },
    "jitjitjit52": {
      "nMsg": 1,
      "avgWordCount": 1
    },
    "haag963": {
      "nMsg": 1,
      "avgWordCount": 11
    },
    "A1steaksauce97": {
      "nMsg": 1,
      "avgWordCount": 1
    },
    "doubledoublerob": {
      "nMsg": 10,
      "avgWordCount": 10.1
    },
    "ThePantyThief": {
      "nMsg": 1,
      "avgWordCount": 3
    },
    "gamebot123": {
      "nMsg": 1,
      "avgWordCount": 3
    },
    "TheRad820": {
      "nMsg": 2,
      "avgWordCount": 1.5
    },
    "Tallb0t": {
      "nMsg": 11,
      "avgWordCount": 8.727272727272727
    },
    "AdStruffer": {
      "nMsg": 9,
      "avgWordCount": 6.333333333333333
    },
    "80lbGorilla": {
      "nMsg": 2,
      "avgWordCount": 7.5
    },
    "McSlacks": {
      "nMsg": 1,
      "avgWordCount": 4
    },
    "NaturallyMorbid": {
      "nMsg": 4,
      "avgWordCount": 9.5
    },
    "ryanmillen94": {
      "nMsg": 1,
      "avgWordCount": 11
    },
    "adamthebraves": {
      "nMsg": 3,
      "avgWordCount": 8
    },
    "Leysfort": {
      "nMsg": 3,
      "avgWordCount": 4.666666666666667
    },
    "clem_chowder_": {
      "nMsg": 15,
      "avgWordCount": 4.933333333333334
    },
    "Dudefacemcgee": {
      "nMsg": 11,
      "avgWordCount": 16.363636363636363
    },
    "battlebot1000": {
      "nMsg": 1,
      "avgWordCount": 9
    },
    "mfstonecutter": {
      "nMsg": 2,
      "avgWordCount": 9
    },
    "jpbenny": {
      "nMsg": 2,
      "avgWordCount": 3.5
    },
    "Dkbasedlord": {
      "nMsg": 16,
      "avgWordCount": 7.25
    },
    "GobyWanKenobi": {
      "nMsg": 4,
      "avgWordCount": 11
    },
    "ajw34": {
      "nMsg": 1,
      "avgWordCount": 2
    },
    "Deffypoo": {
      "nMsg": 1,
      "avgWordCount": 5
    },
    "TheDocVamp": {
      "nMsg": 1,
      "avgWordCount": 40
    },
    "jjolla19": {
      "nMsg": 2,
      "avgWordCount": 25.5
    },
    "YaboiOnTTV": {
      "nMsg": 2,
      "avgWordCount": 2.5
    },
    "LookAdam": {
      "nMsg": 7,
      "avgWordCount": 19.285714285714285
    },
    "indahphoenix": {
      "nMsg": 2,
      "avgWordCount": 13.5
    },
    "RageQuitAndy": {
      "nMsg": 1,
      "avgWordCount": 8
    },
    "woodcock_johnson": {
      "nMsg": 9,
      "avgWordCount": 5.888888888888889
    },
    "mallzeth": {
      "nMsg": 18,
      "avgWordCount": 7.722222222222219
    },
    "GabeRSnerd": {
      "nMsg": 55,
      "avgWordCount": 5.581818181818182
    },
    "parky24": {
      "nMsg": 1,
      "avgWordCount": 7
    },
    "FullMetalRampage": {
      "nMsg": 3,
      "avgWordCount": 3
    },
    "ZachShimer": {
      "nMsg": 1,
      "avgWordCount": 2
    },
    "GnarlesShreddington": {
      "nMsg": 7,
      "avgWordCount": 11.142857142857142
    },
    "CrewHound": {
      "nMsg": 2,
      "avgWordCount": 4
    },
    "tehnoahman11": {
      "nMsg": 3,
      "avgWordCount": 6.333333333333333
    },
    "Araxe11": {
      "nMsg": 4,
      "avgWordCount": 3.5
    },
    "TheSiberg": {
      "nMsg": 1,
      "avgWordCount": 3
    },
    "rdogg1987": {
      "nMsg": 2,
      "avgWordCount": 2.5
    },
    "MOZNIM": {
      "nMsg": 1,
      "avgWordCount": 1
    },
    "YubberLikeRubber": {
      "nMsg": 10,
      "avgWordCount": 3
    },
    "A57R0Z0M813": {
      "nMsg": 3,
      "avgWordCount": 4.333333333333333
    },
    "sonicspike41": {
      "nMsg": 5,
      "avgWordCount": 9.4
    },
    "patrick0d": {
      "nMsg": 1,
      "avgWordCount": 10
    },
    "irisfps1": {
      "nMsg": 1,
      "avgWordCount": 1
    },
    "doeryan": {
      "nMsg": 4,
      "avgWordCount": 5.5
    },
    "dm2264": {
      "nMsg": 1,
      "avgWordCount": 1
    },
    "IAmZackAttack": {
      "nMsg": 1,
      "avgWordCount": 2
    },
    "speedy_gonzalez_1096": {
      "nMsg": 3,
      "avgWordCount": 11.333333333333334
    },
    "Nonalooloo": {
      "nMsg": 12,
      "avgWordCount": 5
    },
    "nannerbots": {
      "nMsg": 1,
      "avgWordCount": 6
    },
    "Bigchunk433": {
      "nMsg": 2,
      "avgWordCount": 6.5
    },
    "Poljasux": {
      "nMsg": 3,
      "avgWordCount": 9
    },
    "CaviarZadi": {
      "nMsg": 1,
      "avgWordCount": 1
    },
    "iamlexdysic": {
      "nMsg": 2,
      "avgWordCount": 4
    },
    "TwO_DiM3nTiOnAl": {
      "nMsg": 1,
      "avgWordCount": 10
    },
    "kMunn": {
      "nMsg": 1,
      "avgWordCount": 1
    },
    "gangstaY0shi": {
      "nMsg": 5,
      "avgWordCount": 7.6
    },
    "Sean0071821": {
      "nMsg": 47,
      "avgWordCount": 3.9787234042553203
    },
    "MartayMcFly": {
      "nMsg": 1,
      "avgWordCount": 2
    },
    "donate2j15": {
      "nMsg": 5,
      "avgWordCount": 2.6
    },
    "milesrussell44": {
      "nMsg": 2,
      "avgWordCount": 11
    },
    "Daylight_MT": {
      "nMsg": 47,
      "avgWordCount": 4.234042553191489
    },
    "athenmrtnz": {
      "nMsg": 2,
      "avgWordCount": 4.5
    },
    "cavecase": {
      "nMsg": 2,
      "avgWordCount": 8
    },
    "OhaiItsAhmad": {
      "nMsg": 11,
      "avgWordCount": 2.909090909090909
    },
    "Halonen": {
      "nMsg": 1,
      "avgWordCount": 1
    },
    "downwithme16": {
      "nMsg": 6,
      "avgWordCount": 4.333333333333333
    },
    "vegaskid96": {
      "nMsg": 2,
      "avgWordCount": 1
    },
    "BlindSimulEx": {
      "nMsg": 14,
      "avgWordCount": 9.571428571428571
    },
    "philsphoreskin": {
      "nMsg": 2,
      "avgWordCount": 3.5
    },
    "theMcRibIsBackGuys": {
      "nMsg": 2,
      "avgWordCount": 7.5
    },
    "jpb647": {
      "nMsg": 2,
      "avgWordCount": 7
    },
    "Gotcha45": {
      "nMsg": 2,
      "avgWordCount": 5
    },
    "Acurra": {
      "nMsg": 1,
      "avgWordCount": 3
    },
    "mollyberry": {
      "nMsg": 1,
      "avgWordCount": 4
    },
    "QuestGEN": {
      "nMsg": 2,
      "avgWordCount": 2
    },
    "McGinnSu": {
      "nMsg": 1,
      "avgWordCount": 2
    },
    "Deffaz": {
      "nMsg": 40,
      "avgWordCount": 4.725
    },
    "OGshazbit": {
      "nMsg": 1,
      "avgWordCount": 14
    },
    "mattresspiano": {
      "nMsg": 1,
      "avgWordCount": 11
    },
    "yuyudude111": {
      "nMsg": 1,
      "avgWordCount": 17
    },
    "BlueHighway": {
      "nMsg": 16,
      "avgWordCount": 8.8125
    },
    "schewbacca": {
      "nMsg": 3,
      "avgWordCount": 11.333333333333334
    },
    "joeythenn": {
      "nMsg": 2,
      "avgWordCount": 3
    },
    "iAmThePaperBoy": {
      "nMsg": 1,
      "avgWordCount": 7
    },
    "itsShiruka": {
      "nMsg": 9,
      "avgWordCount": 5.111111111111111
    },
    "colin503": {
      "nMsg": 7,
      "avgWordCount": 5.857142857142857
    },
    "Frostyscotty": {
      "nMsg": 1,
      "avgWordCount": 7
    },
    "iiiSplatz": {
      "nMsg": 1,
      "avgWordCount": 7
    },
    "celticcanadian": {
      "nMsg": 1,
      "avgWordCount": 1
    },
    "nefariasbread": {
      "nMsg": 2,
      "avgWordCount": 3
    },
    "brightside_64": {
      "nMsg": 1,
      "avgWordCount": 12
    },
    "applecedar": {
      "nMsg": 4,
      "avgWordCount": 4.25
    },
    "MrObakemono": {
      "nMsg": 1,
      "avgWordCount": 7
    },
    "playrAlloy": {
      "nMsg": 1,
      "avgWordCount": 1
    },
    "CrazyChild18": {
      "nMsg": 1,
      "avgWordCount": 1
    },
    "mitcheco": {
      "nMsg": 2,
      "avgWordCount": 10.5
    },
    "JoeHawk215": {
      "nMsg": 6,
      "avgWordCount": 3.1666666666666665
    },
    "freudian_mouse_slip": {
      "nMsg": 4,
      "avgWordCount": 1.5
    },
    "DroopDown": {
      "nMsg": 2,
      "avgWordCount": 4.5
    },
    "tjceltics18": {
      "nMsg": 1,
      "avgWordCount": 1
    },
    "KyleIsReallyBored": {
      "nMsg": 1,
      "avgWordCount": 2
    },
    "abdulghani93": {
      "nMsg": 1,
      "avgWordCount": 3
    },
    "firebird10112": {
      "nMsg": 2,
      "avgWordCount": 8.5
    },
    "Umlaut_A": {
      "nMsg": 24,
      "avgWordCount": 5.541666666666667
    },
    "whatwhatwaitwhatreally": {
      "nMsg": 4,
      "avgWordCount": 2.25
    },
    "nhytmares96": {
      "nMsg": 1,
      "avgWordCount": 11
    },
    "TamPacks": {
      "nMsg": 20,
      "avgWordCount": 7.85
    },
    "Dark_Pinoy": {
      "nMsg": 11,
      "avgWordCount": 5.7272727272727275
    },
    "ForcedExile": {
      "nMsg": 1,
      "avgWordCount": 4
    },
    "TheCasual01": {
      "nMsg": 2,
      "avgWordCount": 7
    },
    "hip_hop_opotamus12": {
      "nMsg": 5,
      "avgWordCount": 7
    },
    "AK_Glob": {
      "nMsg": 1,
      "avgWordCount": 12
    },
    "Empirejerkyusa": {
      "nMsg": 3,
      "avgWordCount": 4.333333333333333
    },
    "silio": {
      "nMsg": 4,
      "avgWordCount": 2
    },
    "PeacefullyBrewed": {
      "nMsg": 4,
      "avgWordCount": 2.5
    },
    "Orca_Dolphin": {
      "nMsg": 1,
      "avgWordCount": 5
    },
    "Irish_Stew1": {
      "nMsg": 8,
      "avgWordCount": 4.5
    },
    "Mattalorian13": {
      "nMsg": 1,
      "avgWordCount": 1
    },
    "gravygravyjosh": {
      "nMsg": 2,
      "avgWordCount": 6
    },
    "dandmanh": {
      "nMsg": 1,
      "avgWordCount": 1
    },
    "dddjdlux": {
      "nMsg": 1,
      "avgWordCount": 16
    },
    "scranklin": {
      "nMsg": 5,
      "avgWordCount": 4.2
    },
    "prazzza": {
      "nMsg": 1,
      "avgWordCount": 2
    },
    "ireonick": {
      "nMsg": 2,
      "avgWordCount": 1
    },
    "Luekoe": {
      "nMsg": 1,
      "avgWordCount": 1
    },
    "XagonogaX": {
      "nMsg": 1,
      "avgWordCount": 3
    },
    "krayt1138": {
      "nMsg": 2,
      "avgWordCount": 4.5
    },
    "dairycans": {
      "nMsg": 4,
      "avgWordCount": 3
    },
    "Saruman______": {
      "nMsg": 4,
      "avgWordCount": 4
    },
    "DarthDravous": {
      "nMsg": 1,
      "avgWordCount": 1
    },
    "JRisJunior": {
      "nMsg": 1,
      "avgWordCount": 1
    },
    "CatalystReactor": {
      "nMsg": 1,
      "avgWordCount": 5
    },
    "SimbaKid": {
      "nMsg": 1,
      "avgWordCount": 1
    },
    "calebhub514": {
      "nMsg": 1,
      "avgWordCount": 1
    },
    "Deadly_Axe": {
      "nMsg": 3,
      "avgWordCount": 1.6666666666666667
    },
    "davidthechemist": {
      "nMsg": 1,
      "avgWordCount": 3
    },
    "ujitter_": {
      "nMsg": 1,
      "avgWordCount": 2
    },
    "imsirmendes": {
      "nMsg": 1,
      "avgWordCount": 10
    },
    "bananafoolery": {
      "nMsg": 2,
      "avgWordCount": 5
    },
    "DareDOOM23": {
      "nMsg": 1,
      "avgWordCount": 4
    },
    "stealthynips": {
      "nMsg": 1,
      "avgWordCount": 5
    },
    "las_lllamas": {
      "nMsg": 1,
      "avgWordCount": 1
    },
    "xOGxMuddbone": {
      "nMsg": 1,
      "avgWordCount": 3
    },
    "TheSnakeandBat": {
      "nMsg": 1,
      "avgWordCount": 6
    },
    "Dishner": {
      "nMsg": 1,
      "avgWordCount": 4
    },
    "Ragin_Blasian": {
      "nMsg": 2,
      "avgWordCount": 3
    },
    "Death_Revelator": {
      "nMsg": 2,
      "avgWordCount": 2
    }
  }
}